dyndnsc/__init__.py
dyndnsc/cli.py
dyndnsc/conf.py
dyndnsc/core.py
dyndnsc/common/__init__.py
dyndnsc/common/constants.py
dyndnsc/common/detect_ip.py
dyndnsc/common/dynamiccli.py
dyndnsc/common/load.py
dyndnsc/common/six.py
dyndnsc/common/subject.py
dyndnsc/detector/__init__.py
dyndnsc/detector/base.py
dyndnsc/detector/builtin.py
dyndnsc/detector/command.py
dyndnsc/detector/dns.py
dyndnsc/detector/dnswanip.py
dyndnsc/detector/iface.py
dyndnsc/detector/manager.py
dyndnsc/detector/null.py
dyndnsc/detector/rand.py
dyndnsc/detector/socket_ip.py
dyndnsc/detector/teredo.py
dyndnsc/detector/webcheck.py
dyndnsc/plugins/__init__.py
dyndnsc/plugins/base.py
dyndnsc/plugins/builtin.py
dyndnsc/plugins/manager.py
dyndnsc/plugins/notify/__init__.py
dyndnsc/resources/__init__.py
dyndnsc/resources/presets.ini
dyndnsc/tests/__init__.py
dyndnsc/tests/test_cli.py
dyndnsc/tests/test_conf.py
dyndnsc/tests/test_console_scripts.py
dyndnsc/tests/test_core.py
dyndnsc/tests/common/__init__.py
dyndnsc/tests/common/test_dynamiccli.py
dyndnsc/tests/common/test_subject.py
dyndnsc/tests/detector/__init__.py
dyndnsc/tests/detector/test_all.py
dyndnsc/tests/detector/test_dnswanip.py
dyndnsc/tests/detector/test_iface.py
dyndnsc/tests/plugins/__init__.py
dyndnsc/tests/plugins/test_base.py
dyndnsc/tests/plugins/test_manager.py
dyndnsc/tests/plugins/notify/__init__.py
dyndnsc/tests/resources/__init__.py
dyndnsc/tests/resources/test_resources.py
dyndnsc/tests/updater/__init__.py
dyndnsc/tests/updater/test_afraid.py
dyndnsc/tests/updater/test_all.py
dyndnsc/tests/updater/test_dnsimple.py
dyndnsc/tests/updater/test_duckdns.py
dyndnsc/tests/updater/test_dyndns2.py
dyndnsc/updater/__init__.py
dyndnsc/updater/afraid.py
dyndnsc/updater/base.py
dyndnsc/updater/builtin.py
dyndnsc/updater/dnsimple.py
dyndnsc/updater/duckdns.py
dyndnsc/updater/dummy.py
dyndnsc/updater/dyndns2.py
dyndnsc/updater/manager.py
dyndnsc-0.6.1.dist-info/AUTHORS
dyndnsc-0.6.1.dist-info/LICENSE
dyndnsc-0.6.1.dist-info/METADATA
dyndnsc-0.6.1.dist-info/WHEEL
dyndnsc-0.6.1.dist-info/entry_points.txt
dyndnsc-0.6.1.dist-info/top_level.txt
dyndnsc-0.6.1.dist-info/RECORD
