Metadata-Version: 2.1
Name: dyndnsc
Version: 0.6.1
Summary: dynamic dns (dyndns) update client with support for multiple protocols
Home-page: https://github.com/infothrill/python-dyndnsc
Author: Paul Kremer
Author-email: paul@spurious.biz
License: MIT License
Keywords: dynamic dns dyndns
Platform: UNKNOWN
Classifier: Development Status :: 4 - Beta
Classifier: Intended Audience :: Developers
Classifier: Intended Audience :: System Administrators
Classifier: License :: DFSG approved
Classifier: License :: OSI Approved
Classifier: License :: OSI Approved :: MIT License
Classifier: Topic :: Internet
Classifier: Topic :: Internet :: Name Service (DNS)
Classifier: Topic :: Software Development :: Libraries :: Python Modules
Classifier: Topic :: System :: Systems Administration
Classifier: Environment :: Console
Classifier: Natural Language :: English
Classifier: Operating System :: MacOS :: MacOS X
Classifier: Operating System :: POSIX :: Linux
Classifier: Operating System :: POSIX :: BSD
Classifier: Programming Language :: Python
Classifier: Programming Language :: Python :: 3.6
Classifier: Programming Language :: Python :: 3.7
Classifier: Programming Language :: Python :: 3.8
Classifier: Programming Language :: Python :: 3.9
Requires-Python: >=3.6
Requires-Dist: daemonocle (>=1.0.1)
Requires-Dist: dnspython (>=1.15.0)
Requires-Dist: netifaces (>=0.10.5)
Requires-Dist: requests (>=2.0.1)
Requires-Dist: json-logging
Requires-Dist: setuptools
